route_distances/__init__.py
route_distances/clustering.py
route_distances/lstm/__init__.py
route_distances/lstm/data.py
route_distances/lstm/defaults.py
route_distances/lstm/features.py
route_distances/lstm/inference.py
route_distances/lstm/models.py
route_distances/lstm/optim.py
route_distances/lstm/utils.py
route_distances/route_distances.py
route_distances/ted/__init__.py
route_distances/ted/distances.py
route_distances/ted/reactiontree.py
route_distances/ted/utils.py
route_distances/tools/__init__.py
route_distances/tools/cluster_aizynth_output.py
route_distances/tools/prepare_aizynthfinder_output.py
route_distances/tools/train_lstm_model.py
route_distances/utils/routes.py
route_distances/utils/type_utils.py
route_distances/validation.py
route_distances-1.2.4.dist-info/LICENSE
route_distances-1.2.4.dist-info/METADATA
route_distances-1.2.4.dist-info/WHEEL
route_distances-1.2.4.dist-info/entry_points.txt
route_distances-1.2.4.dist-info/RECORD
