Metadata-Version: 2.3
Name: route-distances
Version: 1.2.4
Summary: Models for calculating distances between synthesis routes
License: MIT
Author: Genheden, Samuel
Author-email: samuel.genheden@astrazeneca.com
Requires-Python: >=3.9,<3.13
Classifier: License :: OSI Approved :: MIT License
Classifier: Programming Language :: Python :: 3
Classifier: Programming Language :: Python :: 3.9
Classifier: Programming Language :: Python :: 3.10
Classifier: Programming Language :: Python :: 3.11
Classifier: Programming Language :: Python :: 3.12
Requires-Dist: apted (>=1.0.3,<2.0.0)
Requires-Dist: numexpr (<=2.10.0)
Requires-Dist: numpy (>=1.0.0,<2.0.0)
Requires-Dist: optuna (>=2.5.0,<3.0.0)
Requires-Dist: pandas (>=1.0.0,<3.0.0)
Requires-Dist: pydantic (>=2.8.2,<3.0.0)
Requires-Dist: python-dateutil (>=2.8.2,<3.0.0)
Requires-Dist: pytorch-lightning (>=1.6.0,<1.8.4)
Requires-Dist: pytorch-tree-lstm (>=0.1.3,<0.2.0)
Requires-Dist: rdkit (>=2023.9.1,<2024.0.0)
Requires-Dist: scikit-learn (>0.21.0)
Requires-Dist: tables (>=3.6.0,<4.0.0)
Requires-Dist: torch (>=2.0,<2.6)
Project-URL: Documentation, https://molecularai.github.io/route-distances/
Project-URL: Homepage, https://github.com/MolecularAI/route-distances/
Project-URL: Repository, https://github.com/MolecularAI/route-distances/
